eml_extractor.py
eml_extractor-0.1.1.dist-info/LICENSE
eml_extractor-0.1.1.dist-info/METADATA
eml_extractor-0.1.1.dist-info/WHEEL
eml_extractor-0.1.1.dist-info/entry_points.txt
eml_extractor-0.1.1.dist-info/top_level.txt
eml_extractor-0.1.1.dist-info/RECORD
