Metadata-Version: 2.1
Name: eml-extractor
Version: 0.1.1
Summary: A CLI tool to extract attachments from .eml files (email messages saved as files)
Home-page: https://github.com/diogo-alves/eml-extractor
Author: Diogo Alves
Author-email: diogo.alves.ti@gmail.com
License: MIT
Keywords: cli,eml,email,attachments,extract
Platform: any
Classifier: Environment :: Console
Classifier: Programming Language :: Python
Classifier: Programming Language :: Python :: 3 :: Only
Classifier: Programming Language :: Python :: 3.6
Classifier: Programming Language :: Python :: 3.7
Classifier: Programming Language :: Python :: 3.8
Classifier: Programming Language :: Python :: 3.9
Classifier: Operating System :: OS Independent
Classifier: Intended Audience :: End Users/Desktop
Classifier: License :: OSI Approved :: MIT License
Classifier: Natural Language :: English
Classifier: Topic :: Communications :: Email
Classifier: Topic :: Utilities
Requires-Python: >=3.6
License-File: LICENSE
